airoboros/__init__.py
airoboros/embeddings.py
airoboros/entrypoint.py
airoboros/exceptions.py
airoboros/self_instruct.py
airoboros/instructors/__init__.py
airoboros/instructors/agent.py
airoboros/instructors/awareness.py
airoboros/instructors/card.py
airoboros/instructors/character.py
airoboros/instructors/coding.py
airoboros/instructors/contextual.py
airoboros/instructors/cot.py
airoboros/instructors/counterfactual_contextual.py
airoboros/instructors/detailed_writing.py
airoboros/instructors/editor.py
airoboros/instructors/experience.py
airoboros/instructors/general.py
airoboros/instructors/gtkm.py
airoboros/instructors/inline_qa.py
airoboros/instructors/joke.py
airoboros/instructors/misconception.py
airoboros/instructors/multiple_choice.py
airoboros/instructors/orca.py
airoboros/instructors/plan.py
airoboros/instructors/riddle.py
airoboros/instructors/roleplay.py
airoboros/instructors/rp.py
airoboros/instructors/simple_task.py
airoboros/instructors/song.py
airoboros/instructors/stylized_response.py
airoboros/instructors/trivia.py
airoboros/instructors/wordgame.py
airoboros/instructors/writing.py
airoboros/instructors/prompts/agent.txt
airoboros/instructors/prompts/card.txt
airoboros/instructors/prompts/character.txt
airoboros/instructors/prompts/character_awareness.txt
airoboros/instructors/prompts/coding.txt
airoboros/instructors/prompts/contextual.txt
airoboros/instructors/prompts/contextual_response.txt
airoboros/instructors/prompts/cot.txt
airoboros/instructors/prompts/cot_response.txt
airoboros/instructors/prompts/counterfactual_contextual.txt
airoboros/instructors/prompts/counterfactual_contextual_response.txt
airoboros/instructors/prompts/detailed_writing.txt
airoboros/instructors/prompts/detailed_writing_response.txt
airoboros/instructors/prompts/experience.txt
airoboros/instructors/prompts/filter.txt
airoboros/instructors/prompts/general.txt
airoboros/instructors/prompts/gtkm.txt
airoboros/instructors/prompts/joke.txt
airoboros-2.2.2.dist-info/LICENSE
airoboros-2.2.2.dist-info/METADATA
airoboros-2.2.2.dist-info/WHEEL
airoboros-2.2.2.dist-info/entry_points.txt
airoboros-2.2.2.dist-info/top_level.txt
airoboros-2.2.2.dist-info/RECORD
