Metadata-Version: 2.1
Name: airoboros
Version: 2.2.2
Summary: Updated and improved implementation of the self-instruct system.
Home-page: https://github.com/jondurbin/airoboros
Author: Jon Durbin
License: Apache 2.0
Classifier: Development Status :: 4 - Beta
Classifier: Intended Audience :: Developers
Classifier: License :: OSI Approved :: Apache Software License
Classifier: Operating System :: POSIX :: Linux
Classifier: Programming Language :: Python :: 3.10
License-File: LICENSE
Requires-Dist: aiohttp[speedups] >=3.8
Requires-Dist: backoff >=2.2
Requires-Dist: requests >=2.28
Requires-Dist: loguru >=0.7
Requires-Dist: faiss-cpu ==1.7.4
Requires-Dist: sentence-transformers >=2.2.2
Requires-Dist: fastapi >=0.101.0
Requires-Dist: uvicorn >=0.23.0
Requires-Dist: optimum ==1.12.0
Requires-Dist: google-auth ==2.25.1
Provides-Extra: dev
Requires-Dist: black ; extra == 'dev'
Requires-Dist: flake8 ; extra == 'dev'
Provides-Extra: gpu
Requires-Dist: flash-attn >=2.4.2 ; extra == 'gpu'
Requires-Dist: bitsandbytes >=0.40 ; extra == 'gpu'
Requires-Dist: peft ; extra == 'gpu'
Provides-Extra: vllm
Requires-Dist: fschat ; extra == 'vllm'
Requires-Dist: vllm ; extra == 'vllm'
